loganalysis/__init__.py
loganalysis/loganalysis.py
loganalysis/logutilpd.py
loganalysis-0.1.8.dist-info/LICENSE
loganalysis-0.1.8.dist-info/METADATA
loganalysis-0.1.8.dist-info/WHEEL
loganalysis-0.1.8.dist-info/top_level.txt
loganalysis-0.1.8.dist-info/RECORD
