Metadata-Version: 2.1
Name: loganalysis
Version: 0.1.8
Summary: Functions helping with analysis of log files.
Home-page: https://github.com/stbraun/loganalysis
Author: Stefan Braun
Author-email: sb@stbraun.com
License: MIT license
Keywords: loganalysis
Platform: UNKNOWN
Classifier: Development Status :: 2 - Pre-Alpha
Classifier: Intended Audience :: Developers
Classifier: License :: OSI Approved :: MIT License
Classifier: Natural Language :: English
Classifier: Programming Language :: Python :: 3
Classifier: Programming Language :: Python :: 3.8
Classifier: Programming Language :: Python :: 3.9
Requires: pandas
Requires: jupyter_commons
Requires-Dist: pandas
Requires-Dist: jupyter-commons
